LICENSE
MANIFEST.in
README.md
setup.cfg
setup.py
devicehive_plugin/__init__.py
devicehive_plugin/api.py
devicehive_plugin/api_event.py
devicehive_plugin/api_handler.py
devicehive_plugin/command.py
devicehive_plugin/error.py
devicehive_plugin/handler.py
devicehive_plugin/message.py
devicehive_plugin/notification.py
devicehive_plugin/plugin.py
devicehive_plugin/token.py
devicehive_plugin/transport.py
devicehive_plugin.egg-info/PKG-INFO
devicehive_plugin.egg-info/SOURCES.txt
devicehive_plugin.egg-info/dependency_links.txt
devicehive_plugin.egg-info/requires.txt
devicehive_plugin.egg-info/top_level.txt